{
	"sign": {
		"dummy_card_id": 1000780,
		"friend_character": {},
		"missions": [],
		"sugoroku": {
			"dice": {
				"nums": [
					{
						"num": 1,
						"weight": 22
					},
					{
						"num": 2,
						"weight": 22
					},
					{
						"num": 3,
						"weight": 22
					},
					{
						"num": 4,
						"weight": 18
					},
					{
						"num": 5,
						"weight": 10
					},
					{
						"num": 6,
						"weight": 8
					}
				]
			},
			"events": {
				"0": {
					"content": {
						"script_id": 0
					},
					"type": 501
				},
				"10": {
					"content": {
						"rarity": 2
					},
					"type": 102
				},
				"13": {
					"content": {
						"rarity": 2
					},
					"type": 103
				},
				"14": {
					"content": {
						"rarity": 2
					},
					"type": 103
				},
				"15": {
					"content": {
						"rarity": 3
					},
					"type": 103
				},
				"16": {
					"content": {
						"rarity": 2
					},
					"type": 102
				},
				"18": {
					"content": {
						"rarity": 2
					},
					"type": 103
				},
				"19": {
					"content": {
						"rarity": 2
					},
					"type": 103
				},
				"2": {
					"content": {
						"gauge": 2
					},
					"type": 107
				},
				"22": {
					"content": {
						"after_script_id": 0,
						"battle_info": [
							{
								"after_script_id": 2508032,
								"background_id": 26,
								"before_script_id": null,
								"bgm_id": 32,
								"charge_limit": 0,
								"charge_limit_script_id": null,
								"round_id": 50803431
							},
							{
								"after_script_id": 2508033,
								"background_id": 26,
								"before_script_id": null,
								"bgm_id": 30,
								"charge_limit": 0,
								"charge_limit_script_id": null,
								"round_id": 50803432
							},
							{
								"after_script_id": 2508034,
								"background_id": 26,
								"before_script_id": null,
								"bgm_id": 37,
								"charge_limit": 0,
								"charge_limit_script_id": null,
								"round_id": 50803433
							},
							{
								"after_script_id": null,
								"background_id": 26,
								"before_script_id": null,
								"bgm_id": 38,
								"charge_limit": 0,
								"charge_limit_script_id": null,
								"round_id": 50803434
							}
						],
						"battle_round_condition_sets": [],
						"before_script_id": 2508031,
						"enemies": [
							[
								{
									"ai_type": "39 - 12% SA Chance | 1 SA Per Turn",
									"attack": 40580,
									"card_id": 1009961,
									"defence": 4580,
									"enemy_skill_ids": [
										"3100-> Damage Reduction - 47%"
									],
									"exp": 20000,
									"extra_hp_gauges_count": 4,
									"finish_special_inform_hp": 0,
									"first_turn": 0,
									"hp": 1580000,
									"is_finish_special_only": false,
									"is_necessary_to_defeat": true,
									"multi_atk_num": 3,
									"turn": 0,
									"zeni": 2500
								}
							],
							[
								{
									"ai_type": "40 - 20% SA Chance | 1 SA Per Turn",
									"attack": 42580,
									"card_id": 1010181,
									"defence": 7580,
									"enemy_skill_ids": [
										"3100-> Damage Reduction - 47%"
									],
									"exp": 20000,
									"extra_hp_gauges_count": 5,
									"finish_special_inform_hp": 0,
									"first_turn": 0,
									"hp": 1958000,
									"is_finish_special_only": false,
									"is_necessary_to_defeat": true,
									"multi_atk_num": 4,
									"turn": 0,
									"zeni": 2500
								}
							],
							[
								{
									"ai_type": "45 - 15% SA Chance | 1 SA Per Turn",
									"attack": 43000,
									"card_id": 1008591,
									"defence": 9000,
									"enemy_skill_ids": [
										"3110,-> Damage Reduction - 60%"
										"3120,-> Randomly change all ki balls - 35%"
										"3130 -> ATK down - 130, 100"
									],
									"exp": 20000,
									"extra_hp_gauges_count": 6,
									"finish_special_inform_hp": 0,
									"first_turn": 0,
									"hp": 2358000,
									"is_finish_special_only": false,
									"is_necessary_to_defeat": true,
									"multi_atk_num": 5,
									"turn": 0,
									"zeni": 5000
								}
							],
							[
								{
									"additional_drops": [],
									"ai_type": "60 - 18% SA Chance | 1 SA Per Turn",
									"attack": 44000,
									"card_id": 9011801,
									"defence": 10000,
									"drop": {
										"item_id": 5081,
										"quantity": 7,
										"rarity": 3,
										"type": "AwakeningItem"
									},
									"enemy_skill_ids": [
										"3110,-> Damage Reduction - 60%"
										"3120,-> Randomly change all ki balls - 35%"
										"3140 -> ATK down - 135, 100"
									],
									"exp": 60000,
									"extra_hp_gauges_count": 8,
									"finish_special_inform_hp": 0,
									"first_turn": 0,
									"hp": 3158000,
									"is_finish_special_only": false,
									"is_necessary_to_defeat": true,
									"multi_atk_num": 7,
									"turn": 0,
									"zeni": 20000
								}
							]
						]
					},
					"type": 301
				},
				"23": {
					"content": {
						"script_id": 0
					},
					"type": 502
				},
				"24": {
					"content": {
						"gauge": 2
					},
					"type": 107
				},
				"25": {
					"content": {
						"gauge": 2
					},
					"type": 107
				},
				"26": {
					"content": {
						"gauge": 4
					},
					"type": 107
				},
				"27": {
					"content": {
						"gauge": 2
					},
					"type": 107
				},
				"28": {
					"content": {
						"content": {
							"gauge": 3
						},
						"type": 107
					},
					"type": 403
				},
				"32": {
					"content": {
						"gauge": 4
					},
					"type": 107
				},
				"34": {
					"content": {
						"gauge": 2
					},
					"type": 107
				},
				"35": {
					"content": {
						"gauge": 4
					},
					"type": 107
				},
				"37": {
					"content": {
						"gauge": 2
					},
					"type": 107
				},
				"38": {
					"content": {
						"gauge": 2
					},
					"type": 107
				},
				"40": {
					"content": {
						"gauge": 4
					},
					"type": 107
				},
				"41": {
					"content": {
						"gauge": 1
					},
					"type": 107
				},
				"6": {
					"content": {
						"rarity": 2
					},
					"type": 102
				},
				"9": {
					"content": {
						"rarity": 2
					},
					"type": 102
				}
			},
			"first_focus_step": 22,
			"map": "508_003"
		},
		"token": "",
		"user": {}
	}
}